bw_converter/__init__.py
bw_converter/cli.py
bw_converter/converter.py
bw_converter_python-0.0.1.dist-info/METADATA
bw_converter_python-0.0.1.dist-info/WHEEL
bw_converter_python-0.0.1.dist-info/entry_points.txt
bw_converter_python-0.0.1.dist-info/licenses/LICENSE
bw_converter_python-0.0.1.dist-info/RECORD
